PicoMotorDriver.py
KitronikPicoMotorDriver-1.0.0.dist-info/LICENSE
KitronikPicoMotorDriver-1.0.0.dist-info/METADATA
KitronikPicoMotorDriver-1.0.0.dist-info/WHEEL
KitronikPicoMotorDriver-1.0.0.dist-info/top_level.txt
KitronikPicoMotorDriver-1.0.0.dist-info/RECORD
