Metadata-Version: 2.1
Name: KitronikPicoMotorDriver
Version: 1.0.0
Summary: Kitronik Motor Driver Board for Raspberry Pi Pico to drive two motors simultaneously and 4 external connections to GPIO pins
License-File: LICENSE
